domru_intercom_api/__init__.py
domru_intercom_api/exceptions.py
domru_intercom_api/logger.py
domru_intercom_api/schemas.py
domru_intercom_api/wrapper.py
domru_intercom_api-1.1.4.dist-info/licenses/LICENSE
domru_intercom_api-1.1.4.dist-info/METADATA
domru_intercom_api-1.1.4.dist-info/WHEEL
domru_intercom_api-1.1.4.dist-info/top_level.txt
domru_intercom_api-1.1.4.dist-info/RECORD
