Metadata-Version: 2.4
Name: domru_intercom_api
Version: 1.1.4
Summary: API wrapper for managing the dom.ru intercom.
Author-email: regenara <jakebv.22@gmail.com>
License: MIT License
Project-URL: repository, https://github.com/regenara/domru_intercom_api
Project-URL: homepage, https://github.com/regenara/domru_intercom_api
License-File: LICENSE
Requires-Dist: certifi>=2022.0.0
Requires-Dist: pydantic<3.0.0,>=2.0.0
Requires-Dist: aiohttp<4.0.0,>=3.0.0
Dynamic: license-file
